Workbook

Sheet Parámetros
B2: SAVIAS × JoinsClee — Cuadre Financiero
B3: Foco en la FOCA · Área Financiero · Inicio colaboración: 2 de febrero de 2026
B5: PARÁMETROS GLOBALES
B6: TRM (COP por 1 USD) | C6: 3729.27 | D6: TRM oficial del 8 de mayo de 2026 (Banco de la República). Modificá esta celda y todo el archivo se recalcula.
B7: Reparto de beneficios — Lina Toro | C7: 0.7 | D7: 70% para Lina Toro (SAVIAS)
B8: Reparto de beneficios — JoinsClee | C8: 0.3 | D8: 30% para JoinsClee (agencia)
B9: Verificación reparto = 100% | C9: =C7+C8 -> 1
B11: LEYENDA DE CELDAS
B12: Texto azul + fondo amarillo | C12: INPUT EDITABLE | D12: Celdas que vos / Lina llenan manualmente (lo que llegó al banco, gastos reales, etc.)
B13: Texto negro | C13: FÓRMULA | D13: Cálculos automáticos. NO tocar.
B14: Texto verde | C14: LINK ENTRE HOJAS | D14: Pulla datos de otra hoja del libro.
B15: Verde fuerte | C15: TOTAL / SUBTOTAL | D15: Filas de cierre: ingresos totales, gastos totales, beneficio neto.
B17: HOJAS DEL LIBRO
B18: Parámetros | C18: Esta hoja. TRM y % de reparto.
B19: Resumen Mensual | C19: Ingresos − Gastos = Beneficio. Vista de pájaro mes a mes con liquidación.
B20: Ingresos Skool | C20: Pagos enviados por Skool en USD + lo que llegó al banco en COP (input).
B21: Pauta Meta | C21: Detalle de los 25 cobros reales (29 menos 4 fallidos) + columna para lo cobrado por el banco.
B22: Gastos Lina | C22: Suscripciones, pauta, edición de YouTube y video ads que paga Lina.
B23: Gastos JoinsClee | C23: Edición de reels y otros gastos que paga la agencia.
B24: Liquidación | C24: Beneficio neto, reparto 70/30 y devolución de gastos a cada parte.
B26: NOTAS METODOLÓGICAS
B27: • Skool envía pagos los miércoles; Bancolombia los acredita ~viernes (con conversión + comisiones).
B28: • La columna 'COP recibido (real banco)' la llena Lina con lo que efectivamente entró a la cuenta.
B29: • La diferencia entre 'COP esperado (al TRM)' y 'COP recibido (real)' se llama spread + comisiones.
B30: • Los gastos en herramientas y pauta de Lina se devuelven antes del reparto 70/30.
B31: • Los gastos de edición de reels que asumió JoinsClee también se devuelven antes del reparto.
B32: • El beneficio NETO (después de devolver gastos) es lo que se reparte 70/30.

Sheet Resumen Mensual
B2: RESUMEN MENSUAL — Vista de Pájaro
B3: Acumulado del período actual (febrero–mayo 2026). Detalle en cada hoja específica.
B5: INDICADORES PRINCIPALES (acumulado a la fecha)
B6: INGRESOS TOTALES (USD) | C6: ='Ingresos Skool'!E14 -> 4682.21
B7: INGRESOS TOTALES (COP, base liquidación) | C7: ='Liquidación'!D9 -> 17461225
B8: GASTOS TOTALES (COP) | C8: ='Liquidación'!D15 -> 4608796.3
B9: BENEFICIO NETO (COP) | C9: ='Liquidación'!D18 -> 12852429
B10: Margen (%) sobre ingresos | C10: =IFERROR(C9/C7,0) -> 0.73605539
B12: REPARTO DEL BENEFICIO
B13: Parte | C13: % reparto | D13: Beneficio (COP) | E13: Reembolso gastos | F13: TOTAL a recibir
B14: Lina Toro (SAVIAS) | C14: ='Parámetros'!$C$7 -> 0.7 | D14: ='Liquidación'!D22 -> 8996700.3 | E14: ='Liquidación'!C28 -> 3937527.7 | F14: ='Liquidación'!C30 -> 12934228
B15: JoinsClee (Agencia) | C15: ='Parámetros'!$C$8 -> 0.3 | D15: ='Liquidación'!D23 -> 3855728.7 | E15: ='Liquidación'!D28 -> 671268.6 | F15: ='Liquidación'!D30 -> 4526997.3
B16: TOTAL | C16: =C14+C15 -> 1 | D16: =D14+D15 -> 12852429 | E16: =E14+E15 -> 4608796.3 | F16: =F14+F15 -> 17461225
B18: INGRESOS SKOOL POR MES
B19: Mes | C19: USD enviado | D19: COP esperado (TRM) | E19: COP real banco | F19: Spread/comisión
B20: Marzo 2026 | C20: ='Ingresos Skool'!C18 -> 3245.7 | D20: ='Ingresos Skool'!D18 -> 12104092 | E20: ='Ingresos Skool'!E18 -> 0 | F20: =IFERROR(IF(D20=0,0,(E20-D20)/D20),0) -> -1
B21: Abril 2026 | C21: ='Ingresos Skool'!C19 -> 1410.59 | D21: ='Ingresos Skool'!D19 -> 5260471 | E21: ='Ingresos Skool'!E19 -> 0 | F21: =IFERROR(IF(D21=0,0,(E21-D21)/D21),0) -> -1
B22: Mayo 2026 | C22: ='Ingresos Skool'!C20 -> 25.92 | D22: ='Ingresos Skool'!D20 -> 96662.678 | E22: ='Ingresos Skool'!E20 -> 0 | F22: =IFERROR(IF(D22=0,0,(E22-D22)/D22),0) -> -1
B23: TOTAL | C23: =SUM(C20:C22) -> 4682.21 | D23: =SUM(D20:D22) -> 17461225 | E23: =SUM(E20:E22) -> 0 | F23: =IFERROR(IF(D23=0,0,(E23-D23)/D23),0) -> -1
B25: PRÓXIMOS PASOS
B26: 1. Lina llena la columna G de 'Ingresos Skool' con lo que realmente entró en COP a Bancolombia.
B27: 2. Lina llena la celda 'Total realmente cobrado' en hoja 'Pauta Meta' con lo que cobró el banco por la pauta.
B28: 3. Lina añade en 'Gastos Lina' el costo del editor de video ads de la campaña inicial.
B29: 4. Cuando se pague la 2da cuota del editor de YouTube ($900.000 restantes), añadirla en 'Gastos Lina'.
B30: 5. Actualizar TRM en hoja 'Parámetros' (celda C6) si se quiere usar el TRM del día de la liquidación.
B31: 6. A partir del próximo mes, duplicar este libro o agregar columnas mensuales para mantener el histórico.

Sheet Ingresos Skool
B2: INGRESOS SKOOL — Pagos recibidos en cuenta Bancolombia
B3: Skool paga miércoles en USD; Bancolombia acredita viernes en COP (con su propio TRM y comisiones).
B5: Mes | C5: Fecha pago Skool | D5: Concepto | E5: USD enviado | F5: COP esperado (al TRM hoy) | G5: COP recibido (real banco) | H5: Diferencia (spread + comisión) | I5: % spread | J5: Notas
B6: Marzo 2026 | C6: 2026-03-18 | D6: Payout Bancolombia •• 6181 | E6: 1545.25 | F6: =E6*'Parámetros'!$C$6 -> 5762654.5 | H6: =IFERROR(G6-F6,0) -> -5762654.5 | I6: =IFERROR(IF(F6=0,0,(G6-F6)/F6),"") -> -1
B7: Marzo 2026 | C7: 2026-03-25 | D7: Payout Bancolombia •• 6181 | E7: 1700.45 | F7: =E7*'Parámetros'!$C$6 -> 6341437.2 | H7: =IFERROR(G7-F7,0) -> -6341437.2 | I7: =IFERROR(IF(F7=0,0,(G7-F7)/F7),"") -> -1
B8: Abril 2026 | C8: 2026-04-01 | D8: Payout Bancolombia •• 6181 | E8: 25.92 | F8: =E8*'Parámetros'!$C$6 -> 96662.678 | H8: =IFERROR(G8-F8,0) -> -96662.678 | I8: =IFERROR(IF(F8=0,0,(G8-F8)/F8),"") -> -1
B9: Abril 2026 | C9: 2026-04-15 | D9: Payout Bancolombia •• 6181 | E9: 428.98 | F9: =E9*'Parámetros'!$C$6 -> 1599782.2 | H9: =IFERROR(G9-F9,0) -> -1599782.2 | I9: =IFERROR(IF(F9=0,0,(G9-F9)/F9),"") -> -1
B10: Abril 2026 | C10: 2026-04-22 | D10: Payout Bancolombia •• 6181 | E10: 562.06 | F10: =E10*'Parámetros'!$C$6 -> 2096073.5 | H10: =IFERROR(G10-F10,0) -> -2096073.5 | I10: =IFERROR(IF(F10=0,0,(G10-F10)/F10),"") -> -1
B11: Abril 2026 | C11: 2026-04-29 | D11: Payout Bancolombia •• 6181 | E11: 393.63 | F11: =E11*'Parámetros'!$C$6 -> 1467952.6 | H11: =IFERROR(G11-F11,0) -> -1467952.6 | I11: =IFERROR(IF(F11=0,0,(G11-F11)/F11),"") -> -1
B12: Mayo 2026 | C12: 2026-05-06 | D12: Payout Bancolombia •• 6181 | E12: 25.92 | F12: =E12*'Parámetros'!$C$6 -> 96662.678 | H12: =IFERROR(G12-F12,0) -> -96662.678 | I12: =IFERROR(IF(F12=0,0,(G12-F12)/F12),"") -> -1
B14: TOTAL INGRESOS SKOOL | E14: =SUM(E6:E12) -> 4682.21 | F14: =SUM(F6:F12) -> 17461225 | G14: =SUM(G6:G12) -> 0 | H14: =G14-F14 -> -17461225
B16: DESGLOSE POR MES
B17: Mes | C17: USD recibido | D17: COP esperado (TRM) | E17: COP real (banco)
B18: Marzo 2026 | C18: =SUMIF(B6:B12,B18,E6:E12) -> 3245.7 | D18: =SUMIF(B6:B12,B18,F6:F12) -> 12104092 | E18: =SUMIF(B6:B12,B18,G6:G12) -> 0
B19: Abril 2026 | C19: =SUMIF(B6:B12,B19,E6:E12) -> 1410.59 | D19: =SUMIF(B6:B12,B19,F6:F12) -> 5260471 | E19: =SUMIF(B6:B12,B19,G6:G12) -> 0
B20: Mayo 2026 | C20: =SUMIF(B6:B12,B20,E6:E12) -> 25.92 | D20: =SUMIF(B6:B12,B20,F6:F12) -> 96662.678 | E20: =SUMIF(B6:B12,B20,G6:G12) -> 0
E22: Pendiente: $362,55 para el viernes 15

Sheet Pauta Meta
B2: PAUTA META — Cobros reales (Lina paga con MasterCard •• 1260)
B3: Reporte Meta 28/2/2026 – 9/5/2026 · 25 cobros realmente cobrados (29 totales − 4 fallidos)
B5: Fecha | C5: ID transacción | D5: USD cobrado (Meta) | E5: COP esperado (TRM) | F5: Notas
B6: 2026-04-02 | C6: 26572664362423596-26429900946699936 | D6: 15.85 | E6: =D6*'Parámetros'!$C$6 -> 59108.929
B7: 2026-03-24 | C7: 26591968590493175-26265546299802067 | D7: 22.61 | E7: =D7*'Parámetros'!$C$6 -> 84318.795
B8: 2026-03-22 | C8: 26621529580870411-26406222812401089 | D8: 22.61 | E8: =D8*'Parámetros'!$C$6 -> 84318.795
B9: 2026-03-21 | C9: 26468362829520418-26681058464917516 | D9: 1.45 | E9: =D9*'Parámetros'!$C$6 -> 5407.4415
B10: 2026-03-21 | C10: 26468361729520528-26607278612295508 | D10: 11.33 | E10: =D10*'Parámetros'!$C$6 -> 42252.629
B11: 2026-03-21 | C11: 26237165705973460-26357343890622311 | D11: 5.66 | E11: =D11*'Parámetros'!$C$6 -> 21107.668
B12: 2026-03-21 | C12: 26563207766702591-26681055428251153 | D12: 2.83 | E12: =D12*'Parámetros'!$C$6 -> 10553.834
B13: 2026-03-21 | C13: 26681054208251275-26319660774390620 | D13: 1.42 | E13: =D13*'Parámetros'!$C$6 -> 5295.5634
B14: 2026-03-17 | C14: 26562583706764999-26518033244553377 | D14: 22.61 | E14: =D14*'Parámetros'!$C$6 -> 84318.795
B15: 2026-03-15 | C15: 26256860720670626-26294395416917159 | D15: 1.62 | E15: =D15*'Parámetros'!$C$6 -> 6041.4174
B16: 2026-03-15 | C16: 26499869073036461-26233079546382078 | D16: 12.85 | E16: =D16*'Parámetros'!$C$6 -> 47921.12
B17: 2026-03-15 | C17: 26405535969136438-26499868619703173 | D17: 6.43 | E17: =D17*'Parámetros'!$C$6 -> 23979.206
... B30: 2026-03-03 | C30: 26278440451845991-26166803563009679 | D30: 28.56 | E30: =D30*'Parámetros'!$C$6 -> 106507.95
B32: TOTAL PAUTA META (25 cobros reales) | D32: =SUM(D6:D30) -> 325.51 | E32: =SUM(E6:E30) -> 1213914.7
B35: VERIFICACIÓN — Lo que el banco realmente cobró
B36: Concepto | C36: USD | D36: COP (input Lina) | E36: Diferencia vs. esperado | F36: Notas
B37: Total realmente cobrado por el banco | E37: =IFERROR(D37-E32,0) -> -1213914.7 | F37: Cotejar con extracto bancario MasterCard •• 1260

Sheet Gastos Lina
B2: GASTOS QUE ASUME LINA (SAVIAS)
B3: Suscripciones, pauta y producción de video. Estos gastos se devuelven a Lina antes del reparto 70/30.
B5: Concepto | C5: Categoría | D5: Frecuencia | E5: Meses cobrados | F5: Costo USD (input) | G5: Costo COP (input) | H5: Total COP (equivalente) | I5: Notas
B6: Skool | C6: Plataforma comunidad | D6: Mensual | E6: 3 | F6: 99 | H6: =IFERROR(IF(E6="",1,E6),1)*(IFERROR(IF(F6="",0,F6*'Parámetros'!$C$6),0)+IFERROR(IF(G6="",0,G6),0)) -> 1107593.2 | I6: Hosting de la comunidad SAVIAS. Lina ajusta 'Meses cobrados' según los meses realmente facturados desde feb 2026.
B7: Funnelchat | C7: Automatización WhatsApp | D7: Mensual | E7: 3 | F7: 49 | H7: =IFERROR(IF(E7="",1,E7),1)*(IFERROR(IF(F7="",0,F7*'Parámetros'!$C$6),0)+IFERROR(IF(G7="",0,G7),0)) -> 548202.69 | I7: SmartChat / SellerChat / Funnelchat. Verificar cuántos meses se han cobrado.
B8: ManyChat | C8: Automatización Instagram DM | D8: Mensual | E8: 3 | F8: 15 | H8: =IFERROR(IF(E8="",1,E8),1)*(IFERROR(IF(F8="",0,F8*'Parámetros'!$C$6),0)+IFERROR(IF(G8="",0,G8),0)) -> 167817.15 | I8: Triggers JABÓN, PIEL, INICIO, etc. Verificar cuántos meses se han cobrado.
B9: Pauta Meta Ads | C9: Publicidad | D9: Acumulado | E9: 1 | F9: 325.51 | G9: =IFERROR(IF('Pauta Meta'!D37="",0,'Pauta Meta'!D37),0) -> 0 | H9: =IF(G9>0,G9,'Pauta Meta'!E32) -> 1213914.7 | I9: Ver hoja 'Pauta Meta'. Lina llena el COP REAL cobrado por el banco. Mientras no lo llene, se usa el equivalente al TRM.
B10: Edición YouTube — Lazariiio (50%) | C10: Producción audiovisual | D10: 1ra cuota Opción B | E10: 1 | G10: 900000 | H10: =IFERROR(IF(E10="",1,E10),1)*(IFERROR(IF(F10="",0,F10*'Parámetros'!$C$6),0)+IFERROR(IF(G10="",0,G10),0)) -> 900000 | I10: $900.000 COP — primer 50% del paquete mensual de 4 videos (Santiago Giraldo / Lazariiio)
B11: Edición YouTube — Lazariiio (50% restante) | C11: Producción audiovisual | D11: 2da cuota pendiente | E11: 1 | H11: =IFERROR(IF(E11="",1,E11),1)*(IFERROR(IF(F11="",0,F11*'Parámetros'!$C$6),0)+IFERROR(IF(G11="",0,G11),0)) -> 0 | I11: Completar al entregar el último video del mes. Total paquete: $1.800.000 COP
B12: Edición video ads (campaña inicial) | C12: Producción audiovisual | D12: Único | E12: 1 | H12: =IFERROR(IF(E12="",1,E12),1)*(IFERROR(IF(F12="",0,F12*'Parámetros'!$C$6),0)+IFERROR(IF(G12="",0,G12),0)) -> 0 | I12: Lina llena el monto que pagó al editor de los video ads
B13: Otros gastos Lina (1) | C13: Otros | D13: — | E13: 1 | H13: =IFERROR(IF(E13="",1,E13),1)*(IFERROR(IF(F13="",0,F13*'Parámetros'!$C$6),0)+IFERROR(IF(G13="",0,G13),0)) -> 0 | I13: Espacio libre
B14: Otros gastos Lina (2) | C14: Otros | D14: — | E14: 1 | H14: =IFERROR(IF(E14="",1,E14),1)*(IFERROR(IF(F14="",0,F14*'Parámetros'!$C$6),0)+IFERROR(IF(G14="",0,G14),0)) -> 0 | I14: Espacio libre
B16: TOTAL GASTOS LINA | H16: =SUM(H6:H14) -> 3937527.7

Sheet Gastos JoinsClee
B2: GASTOS QUE ASUME JOINSCLEE (Agencia)
B3: Servicios subcontratados por la agencia. Estos gastos se devuelven a JoinsClee antes del reparto 70/30.
B5: Concepto | C5: Categoría | D5: Cantidad | E5: Costo unitario USD | F5: Costo unitario COP | G5: Subtotal USD | H5: Subtotal COP | I5: Notas
B6: Edición de Reels | C6: Producción audiovisual | D6: 10 | E6: 18 | G6: =IFERROR(IF(D6="",0,D6)*IF(E6="",0,E6),0) -> 180 | H6: =G6*'Parámetros'!$C$6+IFERROR(IF(D6="",0,D6)*IF(F6="",0,F6),0) -> 671268.6 | I6: 10 reels × $18 USD
B7: Otros gastos JoinsClee (1) | C7: Otros | G7: =IFERROR(IF(D7="",0,D7)*IF(E7="",0,E7),0) -> 0 | H7: =G7*'Parámetros'!$C$6+IFERROR(IF(D7="",0,D7)*IF(F7="",0,F7),0) -> 0
B8: Otros gastos JoinsClee (2) | C8: Otros | G8: =IFERROR(IF(D8="",0,D8)*IF(E8="",0,E8),0) -> 0 | H8: =G8*'Parámetros'!$C$6+IFERROR(IF(D8="",0,D8)*IF(F8="",0,F8),0) -> 0
B9: Otros gastos JoinsClee (3) | C9: Otros | G9: =IFERROR(IF(D9="",0,D9)*IF(E9="",0,E9),0) -> 0 | H9: =G9*'Parámetros'!$C$6+IFERROR(IF(D9="",0,D9)*IF(F9="",0,F9),0) -> 0
B11: TOTAL GASTOS JOINSCLEE | G11: =SUM(G6:G9) -> 180 | H11: =SUM(H6:H9) -> 671268.6

Sheet Liquidación
B2: LIQUIDACIÓN GENERAL — Cuadre de Cuentas
B3: Reparto: 70% Lina Toro · 30% JoinsClee — sobre beneficio NETO (después de devolver gastos)
B5: 1. INGRESOS
B6: Concepto | C6: USD | D6: COP | E6: Notas
B7: Ingresos Skool (USD enviados) | C7: ='Ingresos Skool'!E14 -> 4682.21 | D7: ='Ingresos Skool'!F14 -> 17461225 | E7: Equivalente al TRM. Para usar el real del banco, ver D8.
B8: Ingresos Skool — COP REAL banco (si Lina llenó la columna G de 'Ingresos Skool') | C8: — | D8: ='Ingresos Skool'!G14 -> 0 | E8: Si está en cero, completar inputs amarillos en hoja 'Ingresos Skool'.
B9: TOTAL INGRESOS (usar real si > 0, si no usar TRM) | C9: ='Ingresos Skool'!E14 -> 4682.21 | D9: =IF(D8>0,D8,D7) -> 17461225 | E9: Esta es la base de ingresos para calcular beneficio.
B11: 2. GASTOS
B12: Concepto | C12: Quién paga | D12: COP | E12: Notas
B13: Gastos asumidos por Lina | C13: Lina | D13: ='Gastos Lina'!H16 -> 3937527.7 | E13: Suscripciones + pauta Meta + edición YouTube + video ads
B14: Gastos asumidos por JoinsClee | C14: JoinsClee | D14: ='Gastos JoinsClee'!H11 -> 671268.6 | E14: Edición de reels y otros servicios subcontratados
B15: TOTAL GASTOS | C15: — | D15: =D13+D14 -> 4608796.3 | E15: Estos gastos se devuelven a quien los pagó antes del reparto.
B17: 3. BENEFICIO NETO
B18: BENEFICIO NETO = Ingresos − Gastos totales | D18: =D9-D15 -> 12852429 | E18: Lo que sobra para repartir 70/30.
B20: 4. REPARTO DEL BENEFICIO (70 / 30)
B21: Parte | C21: % | D21: Beneficio (COP) | E21: Notas
B22: Lina Toro (SAVIAS) | C22: ='Parámetros'!$C$7 -> 0.7 | D22: =$D$18*C22 -> 8996700.3 | E22: 70% del beneficio neto
B23: JoinsClee (Agencia) | C23: ='Parámetros'!$C$8 -> 0.3 | D23: =$D$18*C23 -> 3855728.7 | E23: 30% del beneficio neto
B24: Verificación (debe sumar = beneficio neto) | C24: =C22+C23 -> 1 | D24: =D22+D23 -> 12852429
B26: 5. LIQUIDACIÓN FINAL — ¿Cuánto se queda cada uno?
B27: Concepto | C27: Lina Toro | D27: JoinsClee | E27: Notas
B28: (+) Devolución de gastos asumidos | C28: ='Gastos Lina'!H16 -> 3937527.7 | D28: ='Gastos JoinsClee'!H11 -> 671268.6 | E28: Cada parte recupera lo que adelantó.
B29: (+) Parte del beneficio neto (70 / 30) | C29: =D22 -> 8996700.3 | D29: =D23 -> 3855728.7 | E29: Resultado del reparto del beneficio neto.
B30: TOTAL A RECIBIR | C30: =C28+C29 -> 12934228 | D30: =D28+D29 -> 4526997.3 | E30: Suma final que cada parte se lleva en este período.
B32: Verificación: Total a recibir (Lina + JoinsClee) = Ingresos totales − 0 | C32: =C30+D30 -> 17461225 | D32: =D9 -> 17461225 | E32: Estas dos celdas deben coincidir (ingreso = devolución gastos + beneficio repartido)
B33: Diferencia (debe ser cero) | C33: =C32-D32 -> -3.7252903e-09
